[
    {
        method_name: "TensorLy_Tucker_video_pytorch_truncated_svd_svd",
        method_args: {
            rank: [
                220,
                360,
                202,
                3,
            ],
            n_iter_max: 100,
            init: "svd",
            svd: "truncated_svd",
            random_state: 42,
        },
        qualitative_metrics: {
            Language: "Python",
            Library: "TensorLy",
            "TensorLy backend": "pytorch",
            "Tensor type": "Dense",
            "Data type": "video",
            Platform: "CPU, GPU",
            "Decomposition method": "Tucker",
        },
        quantitative_metrics: {
            gpu_allocated_memory_used_mb: [
                192.23291015625,
                0.0,
                0.0,
                0.0,
                0.0,
                0.0,
                0.0,
                0.0,
                0.0,
                0.0,
            ],
            gpu_cached_memory_used_mb: [
                3072.0,
                2702.0,
                2702.0,
                2704.0,
                2700.0,
                2700.0,
                2700.0,
                2702.0,
                2702.0,
                2700.0,
            ],
            ram_mem_used_mb: [
                2901.43359375,
                2901.6640625,
                2901.6640625,
                2901.6640625,
                2901.6640625,
                2901.6640625,
                2901.6640625,
                2901.6640625,
                2901.6640625,
                2901.6640625,
            ],
            duration: [
                7.00134015083313,
                8.727522134780884,
                5.501197814941406,
                8.476014852523804,
                8.385905027389526,
                8.41270923614502,
                8.350264310836792,
                5.447219610214233,
                8.330436706542969,
                5.384515762329102,
            ],
            frobenius_error: [
                1.3289970345795155,
                1.3289970345795155,
                1.3289970345795155,
                1.3289970345795155,
                1.3289970345795155,
                1.3289970345795155,
                1.3289970345795155,
                1.3289970345795155,
                1.3289970345795155,
                1.3289970345795155,
            ],
            compression_ratio: [
                50.27837471247125,
                50.27837471247125,
                50.27837471247125,
                50.27837471247125,
                50.27837471247125,
                50.27837471247125,
                50.27837471247125,
                50.27837471247125,
                50.27837471247125,
                50.27837471247125,
            ],
        },
    },
    {
        method_name: "TensorLy_Tucker_video_pytorch_truncated_svd_random",
        method_args: {
            rank: [
                220,
                360,
                202,
                3,
            ],
            n_iter_max: 100,
            init: "random",
            svd: "truncated_svd",
            random_state: 42,
        },
        qualitative_metrics: {
            Language: "Python",
            Library: "TensorLy",
            "TensorLy backend": "pytorch",
            "Tensor type": "Dense",
            "Data type": "video",
            Platform: "CPU, GPU",
            "Decomposition method": "Tucker",
        },
        quantitative_metrics: {
            gpu_allocated_memory_used_mb: [
                184.10791015625,
                0.0,
                0.0,
                0.0,
                0.0,
                0.0,
                0.0,
                0.0,
                0.0,
                0.0,
            ],
            gpu_cached_memory_used_mb: [
                2576.0,
                2576.0,
                2576.0,
                2576.0,
                2576.0,
                2576.0,
                2576.0,
                2576.0,
                2576.0,
                2576.0,
            ],
            ram_mem_used_mb: [
                3268.23828125,
                3268.23828125,
                3268.23828125,
                3268.23828125,
                3268.23828125,
                3268.23828125,
                3268.2421875,
                3268.2421875,
                3268.2421875,
                3268.2421875,
            ],
            duration: [
                3.852736711502075,
                3.876776695251465,
                3.89103102684021,
                3.901075839996338,
                3.933765411376953,
                1.1034204959869385,
                3.917942762374878,
                3.9000494480133057,
                3.8782830238342285,
                3.8861260414123535,
            ],
            frobenius_error: [
                1.3289961963891983,
                1.3289961963891983,
                1.3289961963891983,
                1.3289961963891983,
                1.3289961963891983,
                1.3289961963891983,
                1.3289961963891983,
                1.3289961963891983,
                1.3289961963891983,
                1.3289961963891983,
            ],
            compression_ratio: [
                50.27837471247125,
                50.27837471247125,
                50.27837471247125,
                50.27837471247125,
                50.27837471247125,
                50.27837471247125,
                50.27837471247125,
                50.27837471247125,
                50.27837471247125,
                50.27837471247125,
            ],
        },
    },
    {
        method_name: "TensorLy_Tucker_video_pytorch_symeig_svd_random",
        method_args: {
            rank: [
                220,
                360,
                202,
                3,
            ],
            n_iter_max: 100,
            init: "random",
            svd: "symeig_svd",
            random_state: 42,
        },
        qualitative_metrics: {
            Language: "Python",
            Library: "TensorLy",
            "TensorLy backend": "pytorch",
            "Tensor type": "Dense",
            "Data type": "video",
            Platform: "CPU, GPU",
            "Decomposition method": "Tucker",
        },
        quantitative_metrics: {
            gpu_allocated_memory_used_mb: [
                184.10791015625,
                0.0,
                0.0,
                0.0,
                0.0,
                0.0,
                0.0,
                0.0,
                0.0,
                0.0,
            ],
            gpu_cached_memory_used_mb: [
                2578.0,
                2578.0,
                2576.0,
                2578.0,
                2576.0,
                2576.0,
                2576.0,
                2576.0,
                2576.0,
                2576.0,
            ],
            ram_mem_used_mb: [
                3356.06640625,
                3356.18359375,
                3356.17578125,
                3356.16796875,
                3356.16015625,
                3356.2890625,
                3356.2890625,
                3356.2890625,
                3356.2890625,
                3356.2890625,
            ],
            duration: [
                3.896552562713623,
                1.0945649147033691,
                3.8467841148376465,
                3.8891308307647705,
                3.8820228576660156,
                3.8664257526397705,
                3.9178149700164795,
                3.828984498977661,
                3.924654722213745,
                4.055516958236694,
            ],
            frobenius_error: [
                1.3289961963891983,
                1.3289961963891983,
                1.3289961963891983,
                1.3289961963891983,
                1.3289961963891983,
                1.3289961963891983,
                1.3289961963891983,
                1.3289961963891983,
                1.3289961963891983,
                1.3289961963891983,
            ],
            compression_ratio: [
                50.27837471247125,
                50.27837471247125,
                50.27837471247125,
                50.27837471247125,
                50.27837471247125,
                50.27837471247125,
                50.27837471247125,
                50.27837471247125,
                50.27837471247125,
                50.27837471247125,
            ],
        },
    },
    {
        method_name: "TensorLy_Tucker_video_pytorch_randomized_svd_svd",
        method_args: {
            rank: [
                220,
                360,
                202,
                3,
            ],
            n_iter_max: 100,
            init: "svd",
            svd: "randomized_svd",
            random_state: 42,
        },
        qualitative_metrics: {
            Language: "Python",
            Library: "TensorLy",
            "TensorLy backend": "pytorch",
            "Tensor type": "Dense",
            "Data type": "video",
            Platform: "CPU, GPU",
            "Decomposition method": "Tucker",
        },
        quantitative_metrics: {
            gpu_allocated_memory_used_mb: [
                184.10791015625,
                0.0,
                0.0,
                0.0,
                0.0,
                0.0,
                0.0,
                0.0,
                0.0,
                0.0,
            ],
            gpu_cached_memory_used_mb: [
                3576.0,
                3576.0,
                3576.0,
                3578.0,
                3576.0,
                3576.0,
                3574.0,
                3576.0,
                3576.0,
                3574.0,
            ],
            ram_mem_used_mb: [
                3357.02734375,
                3357.01171875,
                3356.99609375,
                3356.98046875,
                3356.96484375,
                3356.94921875,
                3357.3515625,
                3357.48046875,
                3357.46484375,
                3357.44921875,
            ],
            duration: [
                23.969502925872803,
                23.69763708114624,
                26.909228801727295,
                23.925631046295166,
                23.75441265106201,
                23.82596707344055,
                23.976755619049072,
                23.887571334838867,
                24.084398984909058,
                26.708324670791626,
            ],
            frobenius_error: [
                1.3289914466440678,
                1.3289914466440678,
                1.3289914466440678,
                1.3289914466440678,
                1.3289914466440678,
                1.3289914466440678,
                1.3289914466440678,
                1.3289914466440678,
                1.3289914466440678,
                1.3289914466440678,
            ],
            compression_ratio: [
                50.27837471247125,
                50.27837471247125,
                50.27837471247125,
                50.27837471247125,
                50.27837471247125,
                50.27837471247125,
                50.27837471247125,
                50.27837471247125,
                50.27837471247125,
                50.27837471247125,
            ],
        },
    },
    {
        method_name: "TensorLy_Tucker_video_pytorch_randomized_svd_random",
        method_args: {
            rank: [
                220,
                360,
                202,
                3,
            ],
            n_iter_max: 100,
            init: "random",
            svd: "randomized_svd",
            random_state: 42,
        },
        qualitative_metrics: {
            Language: "Python",
            Library: "TensorLy",
            "TensorLy backend": "pytorch",
            "Tensor type": "Dense",
            "Data type": "video",
            Platform: "CPU, GPU",
            "Decomposition method": "Tucker",
        },
        quantitative_metrics: {
            gpu_allocated_memory_used_mb: [
                184.10791015625,
                0.0,
                0.0,
                0.0,
                0.0,
                0.0,
                0.0,
                0.0,
                0.0,
                0.0,
            ],
            gpu_cached_memory_used_mb: [
                2580.0,
                2578.0,
                2578.0,
                2578.0,
                2576.0,
                2578.0,
                2578.0,
                2576.0,
                2576.0,
                2576.0,
            ],
            ram_mem_used_mb: [
                3357.83984375,
                3357.83984375,
                3357.83984375,
                3357.83984375,
                3357.83984375,
                3357.83984375,
                3357.83984375,
                3357.83984375,
                3357.83984375,
                3357.83984375,
            ],
            duration: [
                3.8683066368103027,
                3.9737565517425537,
                3.8420047760009766,
                3.8563578128814697,
                0.985623836517334,
                3.9068102836608887,
                3.930414915084839,
                3.9098012447357178,
                3.960712194442749,
                3.8749468326568604,
            ],
            frobenius_error: [
                1.3289961963891983,
                1.3289961963891983,
                1.3289961963891983,
                1.3289961963891983,
                1.3289961963891983,
                1.3289961963891983,
                1.3289961963891983,
                1.3289961963891983,
                1.3289961963891983,
                1.3289961963891983,
            ],
            compression_ratio: [
                50.27837471247125,
                50.27837471247125,
                50.27837471247125,
                50.27837471247125,
                50.27837471247125,
                50.27837471247125,
                50.27837471247125,
                50.27837471247125,
                50.27837471247125,
                50.27837471247125,
            ],
        },
    },
    {
        method_name: "TensorLy_Tucker_video_numpy_truncated_svd_svd",
        method_args: {
            rank: [
                220,
                360,
                202,
                3,
            ],
            n_iter_max: 100,
            init: "svd",
            svd: "truncated_svd",
            random_state: 42,
        },
        qualitative_metrics: {
            Language: "Python",
            Library: "TensorLy",
            "TensorLy backend": "numpy",
            "Tensor type": "Dense",
            "Data type": "video",
            Platform: "CPU, GPU",
            "Decomposition method": "Tucker",
        },
        quantitative_metrics: {
            gpu_allocated_memory_used_mb: [
                0.0,
                0.0,
                0.0,
                0.0,
                0.0,
                0.0,
                0.0,
                0.0,
                0.0,
                0.0,
            ],
            gpu_cached_memory_used_mb: [
                0.0,
                0.0,
                0.0,
                0.0,
                0.0,
                0.0,
                0.0,
                0.0,
                0.0,
                0.0,
            ],
            ram_mem_used_mb: [
                4425.98046875,
                5160.48828125,
                5163.40625,
                5169.94140625,
                5168.05859375,
                5169.75390625,
                5168.01171875,
                5169.91796875,
                5167.86328125,
                5171.54296875,
            ],
            duration: [
                288.4409885406494,
                294.0121488571167,
                290.9185800552368,
                298.344358921051,
                288.8420605659485,
                295.84006571769714,
                291.4666061401367,
                291.0357413291931,
                294.3809425830841,
                299.5041825771332,
            ],
            frobenius_error: [
                18.7450662193026,
                18.7450662193026,
                18.7450662193026,
                18.7450662193026,
                18.7450662193026,
                18.7450662193026,
                18.7450662193026,
                18.7450662193026,
                18.7450662193026,
                18.7450662193026,
            ],
            compression_ratio: [
                50.27837471247125,
                50.27837471247125,
                50.27837471247125,
                50.27837471247125,
                50.27837471247125,
                50.27837471247125,
                50.27837471247125,
                50.27837471247125,
                50.27837471247125,
                50.27837471247125,
            ],
        },
    },
    {
        method_name: "TensorLy_Tucker_video_numpy_truncated_svd_random",
        method_args: {
            rank: [
                220,
                360,
                202,
                3,
            ],
            n_iter_max: 100,
            init: "random",
            svd: "truncated_svd",
            random_state: 42,
        },
        qualitative_metrics: {
            Language: "Python",
            Library: "TensorLy",
            "TensorLy backend": "numpy",
            "Tensor type": "Dense",
            "Data type": "video",
            Platform: "CPU, GPU",
            "Decomposition method": "Tucker",
        },
        quantitative_metrics: {
            gpu_allocated_memory_used_mb: [
                0.0,
                0.0,
                0.0,
                0.0,
                0.0,
                0.0,
                0.0,
                0.0,
                0.0,
                0.0,
            ],
            gpu_cached_memory_used_mb: [
                0.0,
                0.0,
                0.0,
                0.0,
                0.0,
                0.0,
                0.0,
                0.0,
                0.0,
                0.0,
            ],
            ram_mem_used_mb: [
                5266.7890625,
                6001.3046875,
                5999.19921875,
                6001.4140625,
                5999.734375,
                6001.453125,
                5999.62109375,
                6001.48828125,
                5999.62890625,
                6001.828125,
            ],
            duration: [
                382.22235584259033,
                215.46582674980164,
                211.69708013534546,
                216.4354281425476,
                211.83172035217285,
                217.57974696159363,
                214.50255727767944,
                211.71123456954956,
                211.27815437316895,
                214.23560285568237,
            ],
            frobenius_error: [
                18.745066219302586,
                18.745066219302586,
                18.745066219302586,
                18.745066219302586,
                18.745066219302586,
                18.745066219302586,
                18.745066219302586,
                18.745066219302586,
                18.745066219302586,
                18.745066219302586,
            ],
            compression_ratio: [
                50.27837471247125,
                50.27837471247125,
                50.27837471247125,
                50.27837471247125,
                50.27837471247125,
                50.27837471247125,
                50.27837471247125,
                50.27837471247125,
                50.27837471247125,
                50.27837471247125,
            ],
        },
    },
    {
        method_name: "TensorLy_Tucker_video_numpy_symeig_svd_random",
        method_args: {
            rank: [
                220,
                360,
                202,
                3,
            ],
            n_iter_max: 100,
            init: "random",
            svd: "symeig_svd",
            random_state: 42,
        },
        qualitative_metrics: {
            Language: "Python",
            Library: "TensorLy",
            "TensorLy backend": "numpy",
            "Tensor type": "Dense",
            "Data type": "video",
            Platform: "CPU, GPU",
            "Decomposition method": "Tucker",
        },
        quantitative_metrics: {
            gpu_allocated_memory_used_mb: [
                0.0,
                0.0,
                0.0,
                0.0,
                0.0,
                0.0,
                0.0,
                0.0,
                0.0,
                0.0,
            ],
            gpu_cached_memory_used_mb: [
                0.0,
                0.0,
                0.0,
                0.0,
                0.0,
                0.0,
                0.0,
                0.0,
                0.0,
                0.0,
            ],
            ram_mem_used_mb: [
                5280.66015625,
                6015.23828125,
                6014.24609375,
                6016.6171875,
                6014.5078125,
                6016.56640625,
                6014.2578125,
                6016.7578125,
                6014.25,
                6016.5234375,
            ],
            duration: [
                211.00793743133545,
                213.41261410713196,
                211.21890258789062,
                212.0584225654602,
                214.56569480895996,
                217.08840227127075,
                210.84681725502014,
                218.23827981948853,
                220.0975685119629,
                214.41546368598938,
            ],
            frobenius_error: [
                18.745066219302586,
                18.745066219302586,
                18.745066219302586,
                18.745066219302586,
                18.745066219302586,
                18.745066219302586,
                18.745066219302586,
                18.745066219302586,
                18.745066219302586,
                18.745066219302586,
            ],
            compression_ratio: [
                50.27837471247125,
                50.27837471247125,
                50.27837471247125,
                50.27837471247125,
                50.27837471247125,
                50.27837471247125,
                50.27837471247125,
                50.27837471247125,
                50.27837471247125,
                50.27837471247125,
            ],
        },
    },
    {
        method_name: "TensorLy_Tucker_video_numpy_randomized_svd_svd",
        method_args: {
            rank: [
                220,
                360,
                202,
                3,
            ],
            n_iter_max: 100,
            init: "svd",
            svd: "randomized_svd",
            random_state: 42,
        },
        qualitative_metrics: {
            Language: "Python",
            Library: "TensorLy",
            "TensorLy backend": "numpy",
            "Tensor type": "Dense",
            "Data type": "video",
            Platform: "CPU, GPU",
            "Decomposition method": "Tucker",
        },
        quantitative_metrics: {
            gpu_allocated_memory_used_mb: [
                0.0,
                0.0,
                0.0,
                0.0,
                0.0,
                0.0,
                0.0,
                0.0,
                0.0,
                0.0,
            ],
            gpu_cached_memory_used_mb: [
                0.0,
                0.0,
                0.0,
                0.0,
                0.0,
                0.0,
                0.0,
                0.0,
                0.0,
                0.0,
            ],
            ram_mem_used_mb: [
                5284.33984375,
                6019.01171875,
                6016.99609375,
                6018.9609375,
                6017.6796875,
                6019.42578125,
                6017.56640625,
                6019.1953125,
                6017.51953125,
                6019.72265625,
            ],
            duration: [
                702.328558921814,
                730.1081006526947,
                691.8588452339172,
                723.6177172660828,
                728.8049771785736,
                737.7436716556549,
                720.5483438968658,
                724.5622069835663,
                724.2778222560883,
                728.3602244853973,
            ],
            frobenius_error: [
                18.745066219302583,
                18.745066219302583,
                18.745066219302583,
                18.745066219302583,
                18.745066219302583,
                18.745066219302583,
                18.745066219302583,
                18.745066219302583,
                18.745066219302583,
                18.745066219302583,
            ],
            compression_ratio: [
                50.27837471247125,
                50.27837471247125,
                50.27837471247125,
                50.27837471247125,
                50.27837471247125,
                50.27837471247125,
                50.27837471247125,
                50.27837471247125,
                50.27837471247125,
                50.27837471247125,
            ],
        },
    },
    {
        method_name: "TensorLy_Tucker_video_numpy_randomized_svd_random",
        method_args: {
            rank: [
                220,
                360,
                202,
                3,
            ],
            n_iter_max: 100,
            init: "random",
            svd: "randomized_svd",
            random_state: 42,
        },
        qualitative_metrics: {
            Language: "Python",
            Library: "TensorLy",
            "TensorLy backend": "numpy",
            "Tensor type": "Dense",
            "Data type": "video",
            Platform: "CPU, GPU",
            "Decomposition method": "Tucker",
        },
        quantitative_metrics: {
            gpu_allocated_memory_used_mb: [
                0.0,
                0.0,
                0.0,
                0.0,
                0.0,
                0.0,
                0.0,
                0.0,
                0.0,
                0.0,
            ],
            gpu_cached_memory_used_mb: [
                0.0,
                0.0,
                0.0,
                0.0,
                0.0,
                0.0,
                0.0,
                0.0,
                0.0,
                0.0,
            ],
            ram_mem_used_mb: [
                5367.55859375,
                6101.859375,
                6099.76171875,
                6101.85546875,
                6099.91015625,
                6101.796875,
                6099.8125,
                6101.77734375,
                6099.76953125,
                6101.8046875,
            ],
            duration: [
                213.84989309310913,
                216.74167203903198,
                216.18306922912598,
                224.5012423992157,
                222.41768670082092,
                218.5106167793274,
                221.47381830215454,
                220.42780780792236,
                219.3172128200531,
                223.5318694114685,
            ],
            frobenius_error: [
                18.745066219302586,
                18.745066219302586,
                18.745066219302586,
                18.745066219302586,
                18.745066219302586,
                18.745066219302586,
                18.745066219302586,
                18.745066219302586,
                18.745066219302586,
                18.745066219302586,
            ],
            compression_ratio: [
                50.27837471247125,
                50.27837471247125,
                50.27837471247125,
                50.27837471247125,
                50.27837471247125,
                50.27837471247125,
                50.27837471247125,
                50.27837471247125,
                50.27837471247125,
                50.27837471247125,
            ],
        },
    },
    {
        method_name: "TensorLy_TensorTrain_video_pytorch_truncated_svd",
        method_args: {
            rank: [
                1,
                500,
                302,
                500,
                1,
            ],
            svd: "truncated_svd",
        },
        qualitative_metrics: {
            Language: "Python",
            Library: "TensorLy",
            "TensorLy backend": "pytorch",
            "Tensor type": "Dense",
            "Data type": "video",
            Platform: "CPU, GPU",
            "Decomposition method": "TensorTrain",
        },
        quantitative_metrics: {
            gpu_allocated_memory_used_mb: [
                184.52490234375,
                -0.6044921875,
                0.6044921875,
                -0.6044921875,
                0.6044921875,
                -0.6044921875,
                0.6044921875,
                -0.6044921875,
                0.6044921875,
                -0.6044921875,
            ],
            gpu_cached_memory_used_mb: [
                1846.0,
                1844.0,
                1842.0,
                1844.0,
                1842.0,
                1842.0,
                1842.0,
                1842.0,
                1842.0,
                1842.0,
            ],
            ram_mem_used_mb: [
                3318.3125,
                3318.31640625,
                3318.31640625,
                3318.31640625,
                3318.31640625,
                3318.31640625,
                3318.31640625,
                3318.31640625,
                3318.31640625,
                3318.31640625,
            ],
            duration: [
                0.7087562084197998,
                0.6827812194824219,
                0.6972763538360596,
                0.7001702785491943,
                0.6716737747192383,
                0.6743991374969482,
                0.6763091087341309,
                0.6461403369903564,
                0.6640560626983643,
                0.6618971824645996,
            ],
            frobenius_error: [
                0.26829494163393974,
                0.26829494163393974,
                0.26829494163393974,
                0.26829494163393974,
                0.26829494163393974,
                0.26829494163393974,
                0.26829494163393974,
                0.26829494163393974,
                0.26829494163393974,
                0.26829494163393974,
            ],
            compression_ratio: [
                50.2273362752942,
                50.2273362752942,
                50.2273362752942,
                50.2273362752942,
                50.2273362752942,
                50.2273362752942,
                50.2273362752942,
                50.2273362752942,
                50.2273362752942,
                50.2273362752942,
            ],
        },
    },
    {
        method_name: "TensorLy_TensorTrain_video_pytorch_randomized_svd",
        method_args: {
            rank: [
                1,
                500,
                302,
                500,
                1,
            ],
            svd: "randomized_svd",
        },
        qualitative_metrics: {
            Language: "Python",
            Library: "TensorLy",
            "TensorLy backend": "pytorch",
            "Tensor type": "Dense",
            "Data type": "video",
            Platform: "CPU, GPU",
            "Decomposition method": "TensorTrain",
        },
        quantitative_metrics: {
            gpu_allocated_memory_used_mb: [
                184.52490234375,
                -0.6044921875,
                0.0,
                0.0,
                0.0,
                0.0,
                0.0,
                0.0,
                0.0,
                0.0,
            ],
            gpu_cached_memory_used_mb: [
                1478.0,
                1478.0,
                1478.0,
                1478.0,
                1478.0,
                1478.0,
                1478.0,
                1478.0,
                1478.0,
                1478.0,
            ],
            ram_mem_used_mb: [
                3353.87109375,
                3353.87109375,
                3353.87109375,
                3353.87109375,
                3353.87109375,
                3356.5859375,
                3356.5859375,
                3356.5859375,
                3356.5859375,
                3356.5859375,
            ],
            duration: [
                3.7066988945007324,
                3.713472366333008,
                3.6520512104034424,
                3.663750410079956,
                3.7608888149261475,
                3.719709634780884,
                3.6069464683532715,
                3.6851744651794434,
                3.8549747467041016,
                3.703568696975708,
            ],
            frobenius_error: [
                0.2729927422478795,
                0.2737790811806917,
                0.273058214224875,
                0.27290936559438705,
                0.27285993564873934,
                0.2730347914621234,
                0.2738797338679433,
                0.27299155481159687,
                0.2738173585385084,
                0.2731397747993469,
            ],
            compression_ratio: [
                50.2273362752942,
                50.2273362752942,
                50.2273362752942,
                50.2273362752942,
                50.2273362752942,
                50.2273362752942,
                50.2273362752942,
                50.2273362752942,
                50.2273362752942,
                50.2273362752942,
            ],
        },
    },
    {
        method_name: "TensorLy_TensorTrain_video_numpy_truncated_svd",
        method_args: {
            rank: [
                1,
                500,
                302,
                500,
                1,
            ],
            svd: "truncated_svd",
        },
        qualitative_metrics: {
            Language: "Python",
            Library: "TensorLy",
            "TensorLy backend": "numpy",
            "Tensor type": "Dense",
            "Data type": "video",
            Platform: "CPU, GPU",
            "Decomposition method": "TensorTrain",
        },
        quantitative_metrics: {
            gpu_allocated_memory_used_mb: [
                0.0,
                0.0,
                0.0,
                0.0,
                0.0,
                0.0,
                0.0,
                0.0,
                0.0,
                0.0,
            ],
            gpu_cached_memory_used_mb: [
                0.0,
                0.0,
                0.0,
                0.0,
                0.0,
                0.0,
                0.0,
                0.0,
                0.0,
                0.0,
            ],
            ram_mem_used_mb: [
                4265.12890625,
                4995.51171875,
                4997.48046875,
                4995.51171875,
                4997.48046875,
                4995.51171875,
                4997.48046875,
                4995.51171875,
                4997.48046875,
                4995.51171875,
            ],
            duration: [
                43.29908871650696,
                44.742196798324585,
                43.39942383766174,
                44.45386481285095,
                44.5543429851532,
                44.1021945476532,
                44.43601679801941,
                48.59129095077515,
                44.14046359062195,
                44.16821813583374,
            ],
            frobenius_error: [
                3.7830346102708154,
                3.7830346102708154,
                3.7830346102708154,
                3.7830346102708154,
                3.7830346102708154,
                3.7830346102708154,
                3.7830346102708154,
                3.7830346102708154,
                3.7830346102708154,
                3.7830346102708154,
            ],
            compression_ratio: [
                50.2273362752942,
                50.2273362752942,
                50.2273362752942,
                50.2273362752942,
                50.2273362752942,
                50.2273362752942,
                50.2273362752942,
                50.2273362752942,
                50.2273362752942,
                50.2273362752942,
            ],
        },
    },
    {
        method_name: "TensorLy_TensorTrain_video_numpy_randomized_svd",
        method_args: {
            rank: [
                1,
                500,
                302,
                500,
                1,
            ],
            svd: "randomized_svd",
        },
        qualitative_metrics: {
            Language: "Python",
            Library: "TensorLy",
            "TensorLy backend": "numpy",
            "Tensor type": "Dense",
            "Data type": "video",
            Platform: "CPU, GPU",
            "Decomposition method": "TensorTrain",
        },
        quantitative_metrics: {
            gpu_allocated_memory_used_mb: [
                0.0,
                0.0,
                0.0,
                0.0,
                0.0,
                0.0,
                0.0,
                0.0,
                0.0,
                0.0,
            ],
            gpu_cached_memory_used_mb: [
                0.0,
                0.0,
                0.0,
                0.0,
                0.0,
                0.0,
                0.0,
                0.0,
                0.0,
                0.0,
            ],
            ram_mem_used_mb: [
                5471.390625,
                6201.77734375,
                6203.7421875,
                6201.77734375,
                6203.7421875,
                6201.77734375,
                6205.70703125,
                6201.77734375,
                6203.7421875,
                6201.77734375,
            ],
            duration: [
                339.33749318122864,
                340.56934809684753,
                338.14840483665466,
                332.2791917324066,
                346.78495502471924,
                349.11536407470703,
                341.9490895271301,
                349.2350468635559,
                348.47116899490356,
                385.673424243927,
            ],
            frobenius_error: [
                3.8580100469161938,
                3.8580007249603745,
                3.853319107141974,
                3.8486447734633153,
                3.8481839108453966,
                3.8494923528492846,
                3.851764635659457,
                3.854403662089657,
                3.8574633605661086,
                3.852804855300487,
            ],
            compression_ratio: [
                50.2273362752942,
                50.2273362752942,
                50.2273362752942,
                50.2273362752942,
                50.2273362752942,
                50.2273362752942,
                50.2273362752942,
                50.2273362752942,
                50.2273362752942,
                50.2273362752942,
            ],
        },
    },
    {
        method_name: "T3F_TensorTrain_video",
        method_args: {
            max_tt_rank: [
                1,
                500,
                302,
                500,
                1,
            ],
        },
        qualitative_metrics: {
            Language: "Python",
            Library: "T3F",
            "T3F backend": "tensorflow",
            "Tensor type": "Dense",
            "Data type": "video",
            Platform: "CPU, GPU",
            "Decomposition method": "TensorTrain",
        },
        quantitative_metrics: {
            gpu_allocated_memory_used_mb: [
                183.92138671875,
                0.34814453125,
                1.055419921875,
                -1.055419921875,
                1.056396484375,
                -1.056396484375,
                1.056396484375,
                -1.404541015625,
                2.104736328125,
                -1.407958984375,
            ],
            gpu_cached_memory_used_mb: [
                2647.591064453125,
                366.17431640625,
                0.739013671875,
                0.0,
                0.0,
                0.0,
                0.0,
                0.0,
                0.0,
                0.0,
            ],
            ram_mem_used_mb: [
                2975.4921875,
                2982.76953125,
                2985.42578125,
                2985.48046875,
                2985.60546875,
                2985.64453125,
                2985.66015625,
                2985.6953125,
                2985.76953125,
                2985.80859375,
            ],
            duration: [
                3.030339241027832,
                1.3462798595428467,
                1.408747673034668,
                1.2901065349578857,
                1.4204981327056885,
                0.6621212959289551,
                1.3838257789611816,
                1.247600793838501,
                1.2279584407806396,
                1.2611095905303955,
            ],
            frobenius_error: [
                0.2681734738871455,
                0.2681734738871455,
                0.2681734738871455,
                0.2681734738871455,
                0.2681734738871455,
                0.2681734738871455,
                0.2681734738871455,
                0.2681734738871455,
                0.2681734738871455,
                0.2681734738871455,
            ],
            compression_ratio: [
                50.2273362752942,
                50.2273362752942,
                50.2273362752942,
                50.2273362752942,
                50.2273362752942,
                50.2273362752942,
                50.2273362752942,
                50.2273362752942,
                50.2273362752942,
                50.2273362752942,
            ],
        },
    },
]